djangoldp_ds4go/__init__.py
djangoldp_ds4go/admin.py
djangoldp_ds4go/apps.py
djangoldp_ds4go/translation.py
djangoldp_ds4go/management/__init__.py
djangoldp_ds4go/management/commands/__init__.py
djangoldp_ds4go/management/commands/import_rss.py
djangoldp_ds4go/migrations/0001_initial.py
djangoldp_ds4go/migrations/0002_djangoldp_i18n.py
djangoldp_ds4go/migrations/0003_factbundle.py
djangoldp_ds4go/migrations/__init__.py
djangoldp_ds4go/models/__base_model.py
djangoldp_ds4go/models/__base_named_model.py
djangoldp_ds4go/models/__init__.py
djangoldp_ds4go/models/category.py
djangoldp_ds4go/models/fact.py
djangoldp_ds4go/models/fact_bundle.py
djangoldp_ds4go/models/media.py
djangoldp_ds4go-1.1.2.dist-info/METADATA
djangoldp_ds4go-1.1.2.dist-info/WHEEL
djangoldp_ds4go-1.1.2.dist-info/top_level.txt
djangoldp_ds4go-1.1.2.dist-info/RECORD
