Metadata-Version: 2.4
Name: djangoldp_ds4go
Version: 1.1.2
Summary: djangoldp package for dataspace interoperability framework
Home-page: https://git.startinblox.com/djangoldp-packages/djangoldp-ds4go
Author: Startin'blox
Author-email: jbaptiste@startinblox.com
License: MIT
Classifier: Programming Language :: Python :: 3
Requires-Dist: djangoldp~=5.0.0
Requires-Dist: djangoldp-i18n~=5.0.0
Requires-Dist: djangoldp-edc~=1.0.0
Provides-Extra: include-package-data
Requires-Dist: True; extra == "include-package-data"
